README.txt
setup.py
QiRub/DataParse.py
QiRub/QiRub.py
QiRub/__init__.py
QiRub/crypto.py
QiRub/network.py
QiRub/setup.py
QiRub/updater.py
QiRub.egg-info/PKG-INFO
QiRub.egg-info/SOURCES.txt
QiRub.egg-info/dependency_links.txt
QiRub.egg-info/requires.txt
QiRub.egg-info/top_level.txt